[
  {
    "advert-manager": true
  },
  {
    "advert-slot": true,
    "format": "leaderboard",
    "sizes": "[[728, 90], [900, 250]]",
    "tag": "/6355419/Travel/Europe/France/Paris",
    "targeting": "{\"platform\":\"live\",\"advert-targeting\":\"'platform': 'live'\",\"position\":\"homepagetopslot\"}",
    "id": "advert-1",
    "type": "shaded"
  },
  {
    "advert-slot": true,
    "format": "mpu",
    "sizes": "[[300, 250], [300, 600]]",
    "tag": "/6355419/Travel/Europe/France/Paris",
    "targeting": "{\"platform\":\"live\",\"advert-targeting\":\"'platform': 'live'\",\"position\":\"homepagetopslot\"}",
    "id": "advert-2",
    "label": true
  }
]